{
  "name": "MovieBoxPro",
  "identifier": "io.github.Fjam1571",
  "apps": [
    {
      "beta": false,
      "name": "MovieBoxPro",
      "bundleIdentifier": "com.xd.mbp31",
      "developerName": "MBP Team",
      "subtitle": "MovieboxPro App",
      "version": "9.6",
      "versionDate": "2025-02-07T03:25:29+00:00Z",
      "versionDescription": "Updated to 14.4 on 2025-02-07T03:25:29+00:00Z",
      "downloadURL": "https://www.movieboxpro.app/ipa",
      "localizedDescription": "The best Movie & TVShow App(iOS,Mac,Android,TV,Win,Web)",
      "iconURL": "https://styles.redditmedia.com/t5_29hb17/styles/communityIcon_xmoew2meor5d1.png",
      "tintColor": "9b54fd",
      "size": 48346377,
      "screenshotURLs": [
        "https://images.chuaxin.com/screenshot/ios/64115ed01f734.jpg",
        "https://images.chuaxin.com/screenshot/ios/64115ebe829cf.jpg",
        "https://images.chuaxin.com/screenshot/ios/64115ebc09e0c.jpg"
      ]
    }
  ]
}
